MANIFEST.in
README.rst
setup.py
collective/__init__.py
collective/__init__.pyc
collective.ptg.pikachoose.egg-info/PKG-INFO
collective.ptg.pikachoose.egg-info/SOURCES.txt
collective.ptg.pikachoose.egg-info/dependency_links.txt
collective.ptg.pikachoose.egg-info/entry_points.txt
collective.ptg.pikachoose.egg-info/namespace_packages.txt
collective.ptg.pikachoose.egg-info/not-zip-safe
collective.ptg.pikachoose.egg-info/requires.txt
collective.ptg.pikachoose.egg-info/top_level.txt
collective/ptg/__init__.py
collective/ptg/__init__.pyc
collective/ptg/pikachoose/__init__.py
collective/ptg/pikachoose/__init__.pyc
collective/ptg/pikachoose/configure.zcml
collective/ptg/pikachoose/pikachoose.pt
collective/ptg/pikachoose/resources/1.jpg
collective/ptg/pikachoose/resources/2.jpg
collective/ptg/pikachoose/resources/3.jpg
collective/ptg/pikachoose/resources/4.jpg
collective/ptg/pikachoose/resources/5.jpg
collective/ptg/pikachoose/resources/change_log.txt
collective/ptg/pikachoose/resources/assets/images/75-black.png
collective/ptg/pikachoose/resources/assets/images/black.png
collective/ptg/pikachoose/resources/assets/images/fastf.png
collective/ptg/pikachoose/resources/assets/images/next-horizontal.png
collective/ptg/pikachoose/resources/assets/images/next-vertical.png
collective/ptg/pikachoose/resources/assets/images/next.png
collective/ptg/pikachoose/resources/assets/images/pause.png
collective/ptg/pikachoose/resources/assets/images/play.png
collective/ptg/pikachoose/resources/assets/images/prev-horizontal.png
collective/ptg/pikachoose/resources/assets/images/prev-vertical.png
collective/ptg/pikachoose/resources/assets/images/prev.png
collective/ptg/pikachoose/resources/assets/images/rewind.png
collective/ptg/pikachoose/resources/assets/js/jquery.jcarousel.min.js
collective/ptg/pikachoose/resources/assets/js/jquery.pikachoose.full.js
collective/ptg/pikachoose/resources/assets/js/jquery.pikachoose.js
collective/ptg/pikachoose/resources/bottom/index.html
collective/ptg/pikachoose/resources/bottom/css/styles.css
collective/ptg/pikachoose/resources/css/75-black.png
collective/ptg/pikachoose/resources/css/base.css
collective/ptg/pikachoose/resources/css/basic.png
collective/ptg/pikachoose/resources/css/bottom.css
collective/ptg/pikachoose/resources/css/controls.png
collective/ptg/pikachoose/resources/css/css3.css
collective/ptg/pikachoose/resources/css/espenstyle.css
