Metadata-Version: 1.0
Name: collective.ptg.pikachoose
Version: 1.0.4
Summary: UNKNOWN
Home-page: http://svn.plone.org/svn/collective/
Author: Nathan Van Gheem
Author-email: vangheem@gmail.com
License: GPL
Keywords: plone plonetruegallery pikachoose addon
Platform: UNKNOWN
Classifier: Framework :: Plone
Classifier: Programming Language :: Python
